paddle/__init__.py
paddle/_coupons.py
paddle/_licenses.py
paddle/_modifiers.py
paddle/_one_off_charges.py
paddle/_order_information.py
paddle/_pay_links.py
paddle/_plans.py
paddle/_prices.py
paddle/_product_payments.py
paddle/_products.py
paddle/_subscription_payments.py
paddle/_subscription_users.py
paddle/_transactions.py
paddle/_user_history.py
paddle/_webhooks.py
paddle/constants.py
paddle/paddle.py
paddle/types.py
paddle/validators.py
paddle_client-0.8.1.dist-info/LICENSE.md
paddle_client-0.8.1.dist-info/WHEEL
paddle_client-0.8.1.dist-info/METADATA
paddle_client-0.8.1.dist-info/RECORD
