Metadata-Version: 2.1
Name: paddle-client
Version: 0.8.1
Summary: Python wrapper around the Paddle.com API
Home-page: https://github.com/paddle-python/paddle-client
License: MIT
Keywords: paddle,paddle.com,payments,billing,commerce,finance,saas
Author: Matt Pye
Author-email: pyematt@gmail.com
Requires-Python: >=3.5.2,<4.0.0
Classifier: License :: OSI Approved :: MIT License
Classifier: Programming Language :: Python :: 3
Classifier: Programming Language :: Python :: 3.6
Classifier: Programming Language :: Python :: 3.7
Classifier: Programming Language :: Python :: 3.8
Requires-Dist: requests (>=2.23.0,<3.0.0)
Project-URL: Repository, https://github.com/paddle-python/paddle-client
